multiphenics/__init__.py
multiphenics/fem/BlockAssembler.cpp
multiphenics/fem/BlockAssembler.h
multiphenics/fem/BlockAssemblerBase.cpp
multiphenics/fem/BlockAssemblerBase.h
multiphenics/fem/BlockDirichletBC.cpp
multiphenics/fem/BlockDirichletBC.h
multiphenics/fem/BlockDofMap.cpp
multiphenics/fem/BlockDofMap.h
multiphenics/fem/BlockForm1.cpp
multiphenics/fem/BlockForm1.h
multiphenics/fem/BlockForm2.cpp
multiphenics/fem/BlockForm2.h
multiphenics/fem/BlockFormBase.cpp
multiphenics/fem/BlockFormBase.h
multiphenics/fem/__init__.py
multiphenics/fem/block_adjoint.py
multiphenics/fem/block_assemble.py
multiphenics/fem/block_assembler.py
multiphenics/fem/block_assembler_base.py
multiphenics/fem/block_derivative.py
multiphenics/fem/block_dirichlet_bc.py
multiphenics/fem/block_dof_map.py
multiphenics/fem/block_flatten_nested.py
multiphenics/fem/block_form.py
multiphenics/fem/block_form_1.py
multiphenics/fem/block_form_2.py
multiphenics/fem/block_form_base.py
multiphenics/fem/block_replace_zero.py
multiphenics/fem/block_restrict.py
multiphenics/fem/dirichlet_bc.py
multiphenics/function/BlockFunction.cpp
multiphenics/function/BlockFunction.h
multiphenics/function/BlockFunctionSpace.cpp
multiphenics/function/BlockFunctionSpace.h
multiphenics/function/__init__.py
multiphenics/function/assign.py
multiphenics/function/block_assign.py
multiphenics/function/block_element.py
multiphenics/function/block_function.py
multiphenics/function/block_function_space.py
multiphenics/function/block_split.py
multiphenics/function/block_test_function.py
multiphenics/function/block_test_trial_function_base.py
multiphenics/function/block_trial_function.py
multiphenics/function/split.py
multiphenics/function/test_function.py
multiphenics/function/test_trial_function_base.py
multiphenics/function/trial_function.py
multiphenics/io/__init__.py
multiphenics/io/file.py
multiphenics/io/plot.py
multiphenics/io/xdmf_file.py
multiphenics/la/BlockDefaultFactory.cpp
multiphenics/la/BlockDefaultFactory.h
multiphenics-0.3.0.dist-info/AUTHORS
multiphenics-0.3.0.dist-info/COPYING
multiphenics-0.3.0.dist-info/METADATA
multiphenics-0.3.0.dist-info/WHEEL
multiphenics-0.3.0.dist-info/top_level.txt
multiphenics-0.3.0.dist-info/RECORD
